actualSonLib-0.1.dist-info/DESCRIPTION.rst
actualSonLib-0.1.dist-info/METADATA
actualSonLib-0.1.dist-info/RECORD
actualSonLib-0.1.dist-info/WHEEL
actualSonLib-0.1.dist-info/metadata.json
actualSonLib-0.1.dist-info/top_level.txt
sonLib/__init__.py
sonLib/bioio.py
sonLib/misc.py
sonLib/nxnewick.py
sonLib/nxnewickTest.py
sonLib/nxtree.py
sonLib/nxtreeTest.py
sonLib/tree.py
sonLib/treeTest.py
