Metadata-Version: 2.0
Name: actualSonLib
Version: 0.1
Summary: Small general purpose library for C and Python with focus on bioinformatics.
Home-page: UNKNOWN
Author: Benedict Paten
Author-email: benedict@soe.ucsc.edu
License: UNKNOWN
Platform: UNKNOWN
